flask_postgres/__init__.py
flask_postgres/_compat.py
flask_postgres/config.py
flask_postgres/exceptions.py
flask_postgres/ops.py
flask_postgres/types.py
flask_postgres/utils.py
flask_postgres/cli/__init__.py
flask_postgres/cli/main.py
flask_postgres/cli/types.py
flask_postgres-0.2.5.dist-info/entry_points.txt
flask_postgres-0.2.5.dist-info/LICENSE
flask_postgres-0.2.5.dist-info/WHEEL
flask_postgres-0.2.5.dist-info/METADATA
flask_postgres-0.2.5.dist-info/RECORD
