Metadata-Version: 2.1
Name: flask_postgres
Version: 0.2.5
Summary: Simple CLI for managing Postgres databases in Flask.
Home-page: https://github.com/dwreeves/flask-postgres
License: MIT
Author: Daniel Reeves
Author-email: xdanielreeves@gmail.com
Requires-Python: >=3.7
Classifier: Environment :: Web Environment
Classifier: Framework :: Flask
Classifier: Intended Audience :: Developers
Classifier: License :: OSI Approved :: MIT License
Classifier: Operating System :: OS Independent
Classifier: Programming Language :: Python
Classifier: Programming Language :: Python :: 3
Classifier: Topic :: Internet :: WWW/HTTP :: Dynamic Content
Classifier: Topic :: Software Development :: Libraries :: Python Modules
Classifier: Topic :: Database
Requires-Dist: Flask>=2.0
Requires-Dist: Click>=7.0
Requires-Dist: SQLAlchemy>=1.4.0
Requires-Dist: Flask-SQLAlchemy>=2.5
Requires-Dist: mkdocs ; extra == "doc"
Requires-Dist: pymdown-extensions ; extra == "doc"
Requires-Dist: mkdocs-material ; extra == "doc"
Requires-Dist: mkdocs-macros-plugin ; extra == "doc"
Requires-Dist: pygments ; extra == "doc"
Requires-Dist: rich ; extra == "rich"
Requires-Dist: rich-click ; extra == "rich"
Requires-Dist: pytest>=6.0.1,<7a0 ; extra == "test"
Requires-Dist: pytest-cov ; extra == "test"
Requires-Dist: pytest-postgresql ; extra == "test"
Provides-Extra: doc
Provides-Extra: rich
Provides-Extra: test
